Metadata-Version: 1.0
Name: PyDonate
Version: 0.1
Summary: PyDonate - легкий способ подключения донатов через QIWI для вашего проекта
Home-page: UNKNOWN
Author: UNKNOWN
Author-email: play.fanner@gmail.com
License: UNKNOWN
Platform: UNKNOWN
